upserver/__init__.py
upserver/__main__.py
upserver/cli.py
upserver/config.py
upserver/handlers.py
upserver/logging_config.py
upserver/server.py
upserver/templates.py
upserver/utils.py
upserver-0.2.0.dist-info/licenses/LICENSE
upserver-0.2.0.dist-info/METADATA
upserver-0.2.0.dist-info/WHEEL
upserver-0.2.0.dist-info/entry_points.txt
upserver-0.2.0.dist-info/top_level.txt
upserver-0.2.0.dist-info/RECORD
