Metadata-Version: 2.4
Name: upserver
Version: 0.2.0
Summary: A resumable file server for uploading and downloading files
Home-page: https://github.com/eiAlex/upserver
Author: Álex Vieira
License: MIT
Project-URL: Homepage, https://github.com/eiAlex/upserver
Project-URL: Repository, https://github.com/eiAlex/upserver
Project-URL: Bug Tracker, https://github.com/eiAlex/upserver/issues
Keywords: file server,upload,download,file management
Classifier: Development Status :: 3 - Alpha
Classifier: Intended Audience :: Developers
Classifier: License :: OSI Approved :: MIT License
Classifier: Programming Language :: Python :: 3
Classifier: Programming Language :: Python :: 3.8
Classifier: Programming Language :: Python :: 3.9
Classifier: Programming Language :: Python :: 3.10
Classifier: Programming Language :: Python :: 3.11
Classifier: Programming Language :: Python :: 3.12
Classifier: Topic :: Internet :: WWW/HTTP :: HTTP Servers
Classifier: Topic :: Software Development :: Libraries :: Python Modules
Requires-Python: >=3.7
License-File: LICENSE
Provides-Extra: dev
Requires-Dist: pytest>=9.0.0; extra == "dev"
Requires-Dist: pytest-cov>=6.0.0; extra == "dev"
Requires-Dist: black>=25.0.0; extra == "dev"
Requires-Dist: flake8>=7.0.0; extra == "dev"
Requires-Dist: mypy>=1.19.0; extra == "dev"
Requires-Dist: bandit>=1.9.0; extra == "dev"
Requires-Dist: safety>=3.7.0; extra == "dev"
Requires-Dist: build>=1.3.0; extra == "dev"
Requires-Dist: types-requests>=2.32.0; extra == "dev"
Dynamic: home-page
Dynamic: license-file
Dynamic: requires-python
